{"open_issues":44,"open_pull_requests":0,"active_milestone":null,"latest_release":{"url":"https:\/\/api.github.com\/repos\/wp-cli\/entity-command\/releases\/89193149","assets_url":"https:\/\/api.github.com\/repos\/wp-cli\/entity-command\/releases\/89193149\/assets","upload_url":"https:\/\/uploads.github.com\/repos\/wp-cli\/entity-command\/releases\/89193149\/assets{?name,label}","html_url":"https:\/\/github.com\/wp-cli\/entity-command\/releases\/tag\/v2.4.0","id":89193149,"author":{"login":"schlessera","id":83631,"node_id":"MDQ6VXNlcjgzNjMx","avatar_url":"https:\/\/avatars.githubusercontent.com\/u\/83631?v=4","gravatar_id":"","url":"https:\/\/api.github.com\/users\/schlessera","html_url":"https:\/\/github.com\/schlessera","followers_url":"https:\/\/api.github.com\/users\/schlessera\/followers","following_url":"https:\/\/api.github.com\/users\/schlessera\/following{\/other_user}","gists_url":"https:\/\/api.github.com\/users\/schlessera\/gists{\/gist_id}","starred_url":"https:\/\/api.github.com\/users\/schlessera\/starred{\/owner}{\/repo}","subscriptions_url":"https:\/\/api.github.com\/users\/schlessera\/subscriptions","organizations_url":"https:\/\/api.github.com\/users\/schlessera\/orgs","repos_url":"https:\/\/api.github.com\/users\/schlessera\/repos","events_url":"https:\/\/api.github.com\/users\/schlessera\/events{\/privacy}","received_events_url":"https:\/\/api.github.com\/users\/schlessera\/received_events","type":"User","site_admin":false},"node_id":"RE_kwDOBTKWbc4FUPq9","tag_name":"v2.4.0","target_commitish":"main","name":"Version 2.4.0","draft":false,"prerelease":false,"created_at":"2023-01-12T05:14:36Z","published_at":"2023-01-17T04:32:20Z","assets":[],"tarball_url":"https:\/\/api.github.com\/repos\/wp-cli\/entity-command\/tarball\/v2.4.0","zipball_url":"https:\/\/api.github.com\/repos\/wp-cli\/entity-command\/zipball\/v2.4.0","body":"- Regenerate README file [[#388](https:\/\/github.com\/wp-cli\/entity-command\/pull\/388)]\n- add example for deleting multiple post IDs [[#387](https:\/\/github.com\/wp-cli\/entity-command\/pull\/387)]\n- Add '--field=url' support for posts, comments, and terms [[#383](https:\/\/github.com\/wp-cli\/entity-command\/pull\/383)]\n- Add `wp option get-autoload` and `wp option set-autoload` [[#382](https:\/\/github.com\/wp-cli\/entity-command\/pull\/382)]\n","reactions":{"url":"https:\/\/api.github.com\/repos\/wp-cli\/entity-command\/releases\/89193149\/reactions","total_count":1,"+1":1,"-1":0,"laugh":0,"hooray":0,"confused":0,"heart":0,"rocket":0,"eyes":0}}}